atdate/__init__.py
atdate/api.py
atdate/atdate_format.py
atdate-0.0.1.dev11.dist-info/METADATA
atdate-0.0.1.dev11.dist-info/RECORD
atdate-0.0.1.dev11.dist-info/WHEEL
atdate-0.0.1.dev11.dist-info/top_level.txt
test/__init__.py
test/test_atdate.py
