Metadata-Version: 2.1
Name: atdate
Version: 0.0.1.dev11
Summary: Simple linux at command string parser
Home-page: https://github.com/destag/at-date
Author: Przemysław Pietras
Author-email: przemyslawp94@gmail.com
License: MIT License
Keywords: atdate,at,date,datetime,time,parse,parser
Platform: UNKNOWN
Classifier: License :: OSI Approved :: MIT License
Classifier: Intended Audience :: Developers
Classifier: Programming Language :: Python :: 3.4
Classifier: Programming Language :: Python :: 3.5
Classifier: Programming Language :: Python :: 3.6
Classifier: Programming Language :: Python :: 3.7
Classifier: Programming Language :: Python :: Implementation :: CPython
Classifier: Operating System :: OS Independent
Classifier: Topic :: Software Development
Requires-Dist: lark-parser (>=0.6.3)
Requires-Dist: python-dateutil (>=2.7.3)
